nonebot_plugin_status/__init__.py
nonebot_plugin_status/common.py
nonebot_plugin_status/config.py
nonebot_plugin_status/data_source.py
nonebot_plugin_status/helpers.py
nonebot_plugin_status/onebot_v11.py
nonebot_plugin_status-0.8.0.dist-info/LICENSE
nonebot_plugin_status-0.8.0.dist-info/METADATA
nonebot_plugin_status-0.8.0.dist-info/WHEEL
nonebot_plugin_status-0.8.0.dist-info/RECORD
