Metadata-Version: 2.1
Name: nonebot-plugin-status
Version: 0.8.0
Summary: Check your server status (CPU, Memory, Disk Usage) via nonebot
Home-page: https://github.com/nonebot/plugin-status
License: MIT
Keywords: nonebot,nonebot2,server,status
Author: yanyongyu
Author-email: yyy@nonebot.dev
Requires-Python: >=3.8,<4.0
Classifier: License :: OSI Approved :: MIT License
Classifier: Programming Language :: Python :: 3
Classifier: Programming Language :: Python :: 3.8
Classifier: Programming Language :: Python :: 3.9
Classifier: Programming Language :: Python :: 3.10
Classifier: Programming Language :: Python :: 3.11
Classifier: Programming Language :: Python :: 3.12
Provides-Extra: onebot
Requires-Dist: Jinja2 (>=3.0.0,<4.0.0)
Requires-Dist: humanize (>=4.0.0,<5.0.0)
Requires-Dist: nonebot-adapter-onebot (>=2.0.0-beta.1,<3.0.0) ; extra == "onebot"
Requires-Dist: nonebot2 (>=2.2.0,<3.0.0)
Requires-Dist: psutil (>=5.7.2,<6.0.0)
Project-URL: Documentation, https://github.com/nonebot/plugin-status#readme
Project-URL: Repository, https://github.com/nonebot/plugin-status
